adasamp/__init__.py
adasamp/__version__.py
adasamp/models.py
adasamp/models_sklearn.py
adasamp/sampling.py
adasamp/util.py
adasamp_pareto-1.1.dist-info/LICENSE
adasamp_pareto-1.1.dist-info/METADATA
adasamp_pareto-1.1.dist-info/WHEEL
adasamp_pareto-1.1.dist-info/top_level.txt
adasamp_pareto-1.1.dist-info/RECORD
