Metadata-Version: 2.1
Name: adasamp-pareto
Version: 1.1
Summary: Adaptive bayes-sampling for multi-criteria optimization
Home-page: https://github.com/RaoulHeese/adasamp-pareto
Download-URL: https://github.com/RaoulHeese/adasamp-pareto/releases
Author: Raoul Heese
Author-email: raoul.heese@gmail.com
Maintainer: Raoul Heese
Maintainer-email: raoul.heese@gmail.com
License: MIT
Project-URL: Source Code, https://github.com/RaoulHeese/cadasamp-pareto
License-File: LICENSE
Requires-Dist: numpy
Requires-Dist: scipy
Requires-Dist: scikit-learn
Requires-Dist: dill
Requires-Dist: matplotlib
